{
  "id": 82,
  "name": "gluttony",
  "description": "This Pokémon eats any held Berry triggered by low HP when it falls below 50% of its HP, regardless of the Berry's usual threshold.",
  "flavor_text": "Makes the Pokémon use a held\nBerry earlier than usual.",
  "pokemon_ids": [
    69,
    70,
    71,
    143,
    213,
    263,
    264,
    316,
    317,
    325,
    326,
    446,
    511,
    512,
    513,
    514,
    515,
    516,
    631,
    819,
    820,
    840,
    841,
    842,
    915,
    916,
    1011,
    10091,
    10092,
    10093,
    10112,
    10113,
    10164,
    10174,
    10175,
    10206,
    10216,
    10217,
    10254
  ]
}